tidkvideochange/VideoChange.py
tidkvideochange/__init__.py
tidkvideochange/cli.py
tidkvideochange/detection_batch.py
tidkvideochange/recognition_batch.py
tidkvideochange/tidkvideochange.py
tidkvideochange/utils.py
tidkvideochange/crnnpytorch/__init__.py
tidkvideochange/crnnpytorch/crnn.py
tidkvideochange/crnnpytorch/dataset.py
tidkvideochange/crnnpytorch/utils.py
tidkvideochange/weights/__init__.py
tidkvideochange/weights/crnn.pth
tidkvideochange/weights/frozen_inference_graph.pb
tidkvideochange-0.1.2.dist-info/AUTHORS.rst
tidkvideochange-0.1.2.dist-info/LICENSE
tidkvideochange-0.1.2.dist-info/METADATA
tidkvideochange-0.1.2.dist-info/WHEEL
tidkvideochange-0.1.2.dist-info/entry_points.txt
tidkvideochange-0.1.2.dist-info/top_level.txt
tidkvideochange-0.1.2.dist-info/RECORD
