Metadata-Version: 2.1
Name: tidkvideochange
Version: 0.1.2
Summary: Custom modification of VideoText, incorporating pyscenedetect and batching frames.
Home-page: https://github.com/DominikHuss/tidkvideochange
Author: Dominik Huss
Author-email: dhuss@tidk.pl
License: MIT license
Keywords: tidkvideochange
Platform: UNKNOWN
Classifier: Development Status :: 2 - Pre-Alpha
Classifier: Intended Audience :: Developers
Classifier: License :: OSI Approved :: MIT License
Classifier: Natural Language :: English
Classifier: Programming Language :: Python :: 3.5
Classifier: Programming Language :: Python :: 3.6
Classifier: Programming Language :: Python :: 3.7
Requires-Dist: Click (>=6.0)
Requires-Dist: tqdm
Requires-Dist: six
Requires-Dist: lmdb
Requires-Dist: numpy
Requires-Dist: matplotlib
Requires-Dist: pillow
Requires-Dist: importlib-resources
Requires-Dist: opencv-python
